jdReplace/Logo.svg
jdReplace/__init__.py
jdReplace/__main__.py
jdReplace/version.txt
jdReplace/translations/jdReplace_de.qm
jdReplace/translations/jdReplace_et.qm
jdReplace/translations/jdReplace_fr.qm
jdReplace/translations/jdReplace_it.qm
jdReplace/translations/jdReplace_nl.qm
jdReplace-4.3.dist-info/LICENSE
jdReplace-4.3.dist-info/METADATA
jdReplace-4.3.dist-info/WHEEL
jdReplace-4.3.dist-info/entry_points.txt
jdReplace-4.3.dist-info/top_level.txt
jdReplace-4.3.dist-info/RECORD
